CHANGES.rst
DESCRIPTION.rst
LICENSE
MANIFEST.in
README.md
setup.py
src/kodi/__init__.py
src/kodi/env.py
src/kodi/exports.py
src/kodi/generator.py
src/kodi/guess.py
src/kodi/imports.py
src/kodi/io_utils.py
src/kodi/rename.py
src/kodi/utils.py
src/kodi/xml_utils.py
src/kodi/imdb/__init__.py
src/kodi/imdb/_lib.py
src/kodi/imdb/_series.py
src/kodi/omdb/__init__.py
src/kodi/omdb/_lib.py
src/kodi_nfo_generator.egg-info/PKG-INFO
src/kodi_nfo_generator.egg-info/SOURCES.txt
src/kodi_nfo_generator.egg-info/dependency_links.txt
src/kodi_nfo_generator.egg-info/entry_points.txt
src/kodi_nfo_generator.egg-info/requires.txt
src/kodi_nfo_generator.egg-info/top_level.txt