Metadata-Version: 1.1
Name: kodi-nfo-generator
Version: 0.0.19
Summary:  Simple Python-based command-line tool to generate .nfo files for movies and TV shows for Kodi. 
Home-page: https://github.com/fracpete/kodi-nfo-generator
Author: Peter "fracpete" Reutemann
Author-email: fracpete@gmail.com
License: GNU General Public License version 3.0 (GPLv3)
Platform: UNKNOWN
Classifier: Development Status :: 4 - Beta
Classifier: License :: OSI Approved :: GNU General Public License (GPL)
Classifier: Topic :: Multimedia :: Video
Classifier: Programming Language :: Python :: 3
